odoo10_addon_agreement_sale-10.0.1.0.1-py2.7-nspkg.pth
odoo/addons/agreement_sale/README.rst
odoo/addons/agreement_sale/__init__.py
odoo/addons/agreement_sale/__manifest__.py
odoo/addons/agreement_sale/i18n/es.po
odoo/addons/agreement_sale/i18n/hi_IN.po
odoo/addons/agreement_sale/i18n/hr.po
odoo/addons/agreement_sale/i18n/hr_HR.po
odoo/addons/agreement_sale/i18n/nl.po
odoo/addons/agreement_sale/i18n/nl_NL.po
odoo/addons/agreement_sale/i18n/pt.po
odoo/addons/agreement_sale/i18n/pt_BR.po
odoo/addons/agreement_sale/models/__init__.py
odoo/addons/agreement_sale/models/agreement.py
odoo/addons/agreement_sale/models/sale_order.py
odoo/addons/agreement_sale/views/agreement.xml
odoo/addons/agreement_sale/views/sale_order.xml
odoo/addons/agreement_sale/wizard/__init__.py
odoo/addons/agreement_sale/wizard/sale_make_invoice_advance.py
odoo10_addon_agreement_sale-10.0.1.0.1.dist-info/DESCRIPTION.rst
odoo10_addon_agreement_sale-10.0.1.0.1.dist-info/METADATA
odoo10_addon_agreement_sale-10.0.1.0.1.dist-info/RECORD
odoo10_addon_agreement_sale-10.0.1.0.1.dist-info/WHEEL
odoo10_addon_agreement_sale-10.0.1.0.1.dist-info/metadata.json
odoo10_addon_agreement_sale-10.0.1.0.1.dist-info/namespace_packages.txt
odoo10_addon_agreement_sale-10.0.1.0.1.dist-info/top_level.txt
